src/uart_transceiver.v
module uart_transceiver(
    input wire clk,           // System clock
    input wire rst_n,         // Active low reset
    
    // UART TX Interface
    input wire tx_start,      // Start transmission
    input wire [7:0] tx_data, // Data to transmit
    output reg tx_busy,       // Transmitter busy
    output reg tx,            // Serial output
    
    // UART RX Interface
    input wire rx,            // Serial input
    output reg rx_done,       // Reception complete
    output reg [7:0] rx_data  // Received data
);

    // Parameters for configuring UART
    parameter CLK_FREQ = 50_000_000;  // 50 MHz default clock
    parameter BAUD_RATE = 115200;     // Default baud rate
    parameter CLKS_PER_BIT = CLK_FREQ / BAUD_RATE;
    
    // State definitions
    localparam IDLE = 2'b00;
    localparam START = 2'b01;
    localparam DATA = 2'b10;
    localparam STOP = 2'b11;
    
    // TX logic registers
    reg [1:0] tx_state;
    reg [15:0] tx_clk_count;
    reg [2:0] tx_bit_count;
    reg [7:0] tx_shift_reg;
    
    // RX logic registers
    reg [1:0] rx_state;
    reg [15:0] rx_clk_count;
    reg [2:0] rx_bit_count;
    reg [7:0] rx_shift_reg;
    reg rx_d1, rx_d2;          // Double-flop synchronizer for RX input
    
    // Synchronize RX input to avoid metastability
    always @(posedge clk or negedge rst_n) begin
        if (!rst_n) begin
            rx_d1 <= 1'b1;
            rx_d2 <= 1'b1;
        end else begin
            rx_d1 <= rx;
            rx_d2 <= rx_d1;
        end
    end
    
    // TX state machine
    always @(posedge clk or negedge rst_n) begin
        if (!rst_n) begin
            tx_state <= IDLE;
            tx_clk_count <= 0;
            tx_bit_count <= 0;
            tx_busy <= 0;
            tx <= 1'b1;         // Idle high
            tx_shift_reg <= 8'h00;
        end else begin
            case (tx_state)
                IDLE: begin
                    tx <= 1'b1;  // Idle high
                    tx_clk_count <= 0;
                    tx_bit_count <= 0;
                    
                    if (tx_start && !tx_busy) begin
                        tx_busy <= 1'b1;
                        tx_shift_reg <= tx_data;
                        tx_state <= START;
                    end
                end
                
                START: begin
                    tx <= 1'b0;  // Start bit is low
                    
                    if (tx_clk_count < CLKS_PER_BIT - 1) begin
                        tx_clk_count <= tx_clk_count + 1'b1;
                    end else begin
                        tx_clk_count <= 0;
                        tx_state <= DATA;
                    end
                end
                
                DATA: begin
                    tx <= tx_shift_reg[0];  // LSB first
                    
                    if (tx_clk_count < CLKS_PER_BIT - 1) begin
                        tx_clk_count <= tx_clk_count + 1'b1;
                    end else begin
                        tx_clk_count <= 0;
                        
                        // Shift data
                        tx_shift_reg <= {1'b0, tx_shift_reg[7:1]};
                        
                        if (tx_bit_count < 7) begin
                            tx_bit_count <= tx_bit_count + 1'b1;
                        end else begin
                            tx_bit_count <= 0;
                            tx_state <= STOP;
                        end
                    end
                end
                
                STOP: begin
                    tx <= 1'b1;  // Stop bit is high
                    
                    if (tx_clk_count < CLKS_PER_BIT - 1) begin
                        tx_clk_count <= tx_clk_count + 1'b1;
                    end else begin
                        tx_clk_count <= 0;
                        tx_busy <= 1'b0;
                        tx_state <= IDLE;
                    end
                end
                
                default: tx_state <= IDLE;
            endcase
        end
    end
    
    // RX state machine
    always @(posedge clk or negedge rst_n) begin
        if (!rst_n) begin
            rx_state <= IDLE;
            rx_clk_count <= 0;
            rx_bit_count <= 0;
            rx_done <= 0;
            rx_data <= 8'h00;
            rx_shift_reg <= 8'h00;
        end else begin
            // Clear rx_done flag after one clock cycle
            if (rx_done) rx_done <= 1'b0;
            
            case (rx_state)
                IDLE: begin
                    rx_clk_count <= 0;
                    rx_bit_count <= 0;
                    
                    // Detect start bit (falling edge)
                    if (rx_d2 == 1'b0) begin
                        rx_state <= START;
                    end
                end
                
                START: begin
                    // Sample in the middle of the start bit
                    if (rx_clk_count == (CLKS_PER_BIT - 1) / 2) begin
                        // Confirm it's still low (valid start bit)
                        if (rx_d2 == 1'b0) begin
                            rx_clk_count <= rx_clk_count + 1'b1;
                        end else begin
                            // False start, go back to IDLE
                            rx_state <= IDLE;
                        end
                    end else if (rx_clk_count < CLKS_PER_BIT - 1) begin
                        rx_clk_count <= rx_clk_count + 1'b1;
                    end else begin
                        rx_clk_count <= 0;
                        rx_state <= DATA;
                    end
                end
                
                DATA: begin
                    // Sample in the middle of each data bit
                    if (rx_clk_count == (CLKS_PER_BIT - 1) / 2) begin
                        rx_shift_reg <= {rx_d2, rx_shift_reg[7:1]};  // LSB first
                        rx_clk_count <= rx_clk_count + 1'b1;
                    end else if (rx_clk_count < CLKS_PER_BIT - 1) begin
                        rx_clk_count <= rx_clk_count + 1'b1;
                    end else begin
                        rx_clk_count <= 0;
                        
                        if (rx_bit_count < 7) begin
                            rx_bit_count <= rx_bit_count + 1'b1;
                        end else begin
                            rx_bit_count <= 0;
                            rx_state <= STOP;
                        end
                    end
                end
                
                STOP: begin
                    // Sample in the middle of the stop bit
                    if (rx_clk_count < CLKS_PER_BIT - 1) begin
                        rx_clk_count <= rx_clk_count + 1'b1;
                    end else begin
                        // Reception complete
                        rx_done <= 1'b1;
                        rx_data <= rx_shift_reg;
                        rx_state <= IDLE;
                    end
                end
                
                default: rx_state <= IDLE;
            endcase
        end
    end

endmodule

src/uart_transceiver_tb.v
`timescale 1ns/1ps

module uart_transceiver_tb();

    // Test parameters
    parameter CLK_PERIOD = 20; // 50 MHz clock (20ns period)
    parameter BAUD_RATE = 115200;
    parameter BIT_PERIOD = 1000000000/BAUD_RATE; // Bit period in ns
    
    // Testbench signals
    reg clk;
    reg rst_n;
    
    // TX signals
    reg tx_start;
    reg [7:0] tx_data;
    wire tx_busy;
    wire tx_out;
    
    // RX signals
    wire rx_done;
    wire [7:0] rx_data;
    
    // Loopback: connect TX output to RX input
    wire loopback;
    assign loopback = tx_out;
    
    // Test data
    reg [7:0] test_data [0:9];
    integer i;
    
    // Instantiate the UART transceiver
    uart_transceiver #(
        .CLK_FREQ(50_000_000),
        .BAUD_RATE(115200)
    ) uut (
        .clk(clk),
        .rst_n(rst_n),
        .tx_start(tx_start),
        .tx_data(tx_data),
        .tx_busy(tx_busy),
        .tx(tx_out),
        .rx(loopback),
        .rx_done(rx_done),
        .rx_data(rx_data)
    );
    
    // Clock generation
    initial begin
        clk = 0;
        forever #(CLK_PERIOD/2) clk = ~clk;
    end
    
    // Monitor for received data
    always @(posedge rx_done) begin
        $display("Time %0t: Received data: 0x%h", $time, rx_data);
        if (rx_data == tx_data)
            $display("Data matched successfully!");
        else
            $display("ERROR: Data mismatch! Expected: 0x%h, Got: 0x%h", tx_data, rx_data);
    end
    
    // Main test procedure
    initial begin
        // Initialize test data
        test_data[0] = 8'h55; // Alternating 0s and 1s
        test_data[1] = 8'hAA; // Alternating 1s and 0s
        test_data[2] = 8'h00; // All 0s
        test_data[3] = 8'hFF; // All 1s
        test_data[4] = 8'h01; // Single bit
        test_data[5] = 8'h80; // Single bit (MSB)
        test_data[6] = 8'h33; // Some pattern
        test_data[7] = 8'hCC; // Another pattern
        test_data[8] = 8'hA5; // Mixed pattern
        test_data[9] = 8'h5A; // Mixed pattern
        
        // Initialize signals
        rst_n = 0;
        tx_start = 0;
        tx_data = 0;
        
        // Apply reset
        #100;
        rst_n = 1;
        #100;
        
        // Test each data value
        for (i = 0; i < 10; i = i + 1) begin
            // Wait for any previous transmission to complete
            wait(!tx_busy);
            
            // Prepare transmission
            @(posedge clk);
            tx_data = test_data[i];
            $display("\nTime %0t: Transmitting data: 0x%h", $time, tx_data);
            
            // Start transmission
            tx_start = 1;
            @(posedge clk);
            tx_start = 0;
            
            // Wait for transmission to complete and reception to be done
            wait(rx_done);
            #100; // Wait a bit more
        end
        
        // End simulation
        #5000;
        $display("\nUART Transceiver Test Complete");
        $finish;
    end
    
    // Generate waveform file
    initial begin
        $dumpfile("uart_transceiver_tb.vcd");
        $dumpvars(0, uart_transceiver_tb);
    end

endmodule

src/uart_transceiver_tb.vcd
$date
	Sun Aug 10 20:24:28 2025
$end
$version
	ModelSim Version 2020.1
$end
$timescale
	1ps
$end

$scope module uart_transceiver_tb $end
$var parameter 32 ! CLK_PERIOD $end
$var parameter 32 " BAUD_RATE $end
$var parameter 32 # BIT_PERIOD $end
$var reg 1 $ clk $end
$var reg 1 % rst_n $end
$var reg 1 & tx_start $end
$var reg 8 ' tx_data [7:0] $end
$var wire 1 ( tx_busy $end
$var wire 1 ) tx_out $end
$var wire 1 * rx_done $end
$var wire 1 + rx_data [7] $end
$var wire 1 , rx_data [6] $end
$var wire 1 - rx_data [5] $end
$var wire 1 . rx_data [4] $end
$var wire 1 / rx_data [3] $end
$var wire 1 0 rx_data [2] $end
$var wire 1 1 rx_data [1] $end
$var wire 1 2 rx_data [0] $end
$var wire 1 3 loopback $end
$var integer 32 4 i $end

$scope module uut $end
$var parameter 32 5 CLK_FREQ $end
$var parameter 32 6 BAUD_RATE $end
$var parameter 32 7 CLKS_PER_BIT $end
$var parameter 2 8 IDLE $end
$var parameter 2 9 START $end
$var parameter 2 : DATA $end
$var parameter 2 ; STOP $end
$var wire 1 < clk $end
$var wire 1 = rst_n $end
$var wire 1 > tx_start $end
$var wire 1 ? tx_data [7] $end
$var wire 1 @ tx_data [6] $end
$var wire 1 A tx_data [5] $end
$var wire 1 B tx_data [4] $end
$var wire 1 C tx_data [3] $end
$var wire 1 D tx_data [2] $end
$var wire 1 E tx_data [1] $end
$var wire 1 F tx_data [0] $end
$var reg 1 G tx_busy $end
$var reg 1 H tx $end
$var wire 1 3 rx $end
$var reg 1 I rx_done $end
$var reg 8 J rx_data [7:0] $end
$var reg 2 K tx_state [1:0] $end
$var reg 16 L tx_clk_count [15:0] $end
$var reg 3 M tx_bit_count [2:0] $end
$var reg 8 N tx_shift_reg [7:0] $end
$var reg 2 O rx_state [1:0] $end
$var reg 16 P rx_clk_count [15:0] $end
$var reg 3 Q rx_bit_count [2:0] $end
$var reg 8 R rx_shift_reg [7:0] $end
$var reg 1 S rx_d1 $end
$var reg 1 T rx_d2 $end
$upscope $end
$upscope $end
$enddefinitions $end
#0
$dumpvars
0$
0%
0&
b0 '
0G
1H
0I
b0 J
b0 K
b0 L
b0 M
b0 N
b0 O
b0 P
b0 Q
b0 R
1S
1T
b10100 !
b11100001000000000 "
b10000111101000 #
b10111110101111000010000000 5
b11100001000000000 6
b110110010 7
b0 8
b1 9
b10 :
b11 ;
bx 4
0(
1)
0*
02
01
00
0/
0.
0-
0,
0+
13
0F
0E
0D
0C
0B
0A
0@
0?
0>
0=
0<
$end
#10000
1$
1<
#20000
0$
0<
#30000
1$
1<
#40000
0$
0<
#50000
1$
1<
#60000
0$
0<
#70000
1$
1<
#80000
0$
0<
#90000
1$
1<
#100000
1%
0$
1=
0<
#110000
1$
1<
#120000
0$
0<
#130000
1$
1<
#140000
0$
0<
#150000
1$
1<
#160000
0$
0<
#170000
1$
1<
#180000
0$
0<
#190000
1$
1<
#200000
b0 4
0$
0<
#210000
1$
1<
b1010101 '
1&
1F
1D
1B
1@
1>
#220000
0$
0<
#230000
1$
1<
0&
0>
1G
b1010101 N
b1 K
1(
#240000
0$
0<
#250000
1$
1<
0H
b1 L
0)
03
#260000
0$
0<
#270000
1$
1<
0S
b10 L
#280000
0$
0<
#290000
1$
1<
0T
b11 L
#300000
0$
0<
#310000
1$
1<
b100 L
b1 O
#320000
0$
0<
#330000
1$
1<
b101 L
b1 P
#340000
0$
0<
#350000
1$
1<
b110 L
b10 P
#360000
0$
0<
#370000
1$
1<
b111 L
b11 P
#380000
0$
0<
#390000
1$
1<
b1000 L
b100 P
#400000
0$
0<
#410000
1$
1<
b1001 L
b101 P
#420000
0$
0<
#430000
1$
1<
b1010 L
b110 P
#440000
0$
0<
#450000
1$
1<
b1011 L
b111 P
#460000
0$
0<
#470000
1$
1<
b1100 L
b1000 P
#480000
0$
0<
#490000
1$
1<
b1101 L
b1001 P
#500000
0$
0<
#510000
1$
1<
b1110 L
b1010 P
#520000
0$
0<
#530000
1$
1<
b1111 L
b1011 P
#540000
0$
0<
#550000
1$
1<
b10000 L
b1100 P
#560000
0$
0<
#570000
1$
1<
b10001 L
b1101 P
#580000
0$
0<
#590000
1$
1<
b10010 L
b1110 P
#600000
0$
0<
#610000
1$
1<
b10011 L
b1111 P
#620000
0$
0<
#630000
1$
1<
b10100 L
b10000 P
#640000
0$
0<
#650000
1$
1<
b10101 L
b10001 P
#660000
0$
0<
#670000
1$
1<
b10110 L
b10010 P
#680000
0$
0<
#690000
1$
1<
b10111 L
b10011 P
#700000
0$
0<
#710000
1$
1<
b11000 L
b10100 P
#720000
0$
0<
#730000
1$
1<
b11001 L
b10101 P
#740000
0$
0<
#750000
1$
1<
b11010 L
b10110 P
#760000
0$
0<
#770000
1$
1<
b11011 L
b10111 P
#780000
0$
0<
#790000
1$
1<
b11100 L
b11000 P
#800000
0$
0<
#810000
1$
1<
b11101 L
b11001 P
#820000
0$
0<
#830000
1$
1<
b11110 L
b11010 P
#840000
0$
0<
#850000
1$
1<
b11111 L
b11011 P
#860000
0$
0<
#870000
1$
1<
b100000 L
b11100 P
#880000
0$
0<
#890000
1$
1<
b100001 L
b11101 P
#900000
0$
0<
#910000
1$
1<
b100010 L
b11110 P
#920000
0$
0<
#930000
1$
1<
b100011 L
b11111 P
#940000
0$
0<
#950000
1$
1<
b100100 L
b100000 P
#960000
0$
0<
#970000
1$
1<
b100101 L
b100001 P
#980000
0$
0<
#990000
1$
1<
b100110 L
b100010 P
#1000000
0$
0<
#1010000
1$
1<
b100111 L
b100011 P
#1020000
0$
0<
#1030000
1$
1<
b101000 L
b100100 P
#1040000
0$
0<
#1050000
1$
1<
b101001 L
b100101 P
#1060000
0$
0<
#1070000
1$
1<
b101010 L
b100110 P
#1080000
0$
0<
#1090000
1$
1<
b101011 L
b100111 P
#1100000
0$
0<
#1110000
1$
1<
b101100 L
b101000 P
#1120000
0$
0<
#1130000
1$
1<
b101101 L
b101001 P
#1140000
0$
0<
#1150000
1$
1<
b101110 L
b101010 P
#1160000
0$
0<
#1170000
1$
1<
b101111 L
b101011 P
#1180000
0$
0<
#1190000
1$
1<
b110000 L
b101100 P
#1200000
0$
0<
#1210000
1$
1<
b110001 L
b101101 P
#1220000
0$
0<
#1230000
1$
1<
b110010 L
b101110 P
#1240000
0$
0<
#1250000
1$
1<
b110011 L
b101111 P
#1260000
0$
0<
#1270000
1$
1<
b110100 L
b110000 P
#1280000
0$
0<
#1290000
1$
1<
b110101 L
b110001 P
#1300000
0$
0<
#1310000
1$
1<
b110110 L
b110010 P
#1320000
0$
0<
#1330000
1$
1<
b110111 L
b110011 P
#1340000
0$
0<
#1350000
1$
1<
b111000 L
b110100 P
#1360000
0$
0<
#1370000
1$
1<
b111001 L
b110101 P
#1380000
0$
0<
#1390000
1$
1<
b111010 L
b110110 P
#1400000
0$
0<
#1410000
1$
1<
b111011 L
b110111 P
#1420000
0$
0<
#1430000
1$
1<
b111100 L
b111000 P
#1440000
0$
0<
#1450000
1$
1<
b111101 L
b111001 P
#1460000
0$
0<
#1470000
1$
1<
b111110 L
b111010 P
#1480000
0$
0<
#1490000
1$
1<
b111111 L
b111011 P
#1500000
0$
0<
#1510000
1$
1<
b1000000 L
b111100 P
#1520000
0$
0<
#1530000
1$
1<
b1000001 L
b111101 P
#1540000
0$
0<
#1550000
1$
1<
b1000010 L
b111110 P
#1560000
0$
0<
#1570000
1$
1<
b1000011 L
b111111 P
#1580000
0$
0<
#1590000
1$
1<
b1000100 L
b1000000 P
#1600000
0$
0<
#1610000
1$
1<
b1000101 L
b1000001 P
#1620000
0$
0<
#1630000
1$
1<
b1000110 L
b1000010 P
#1640000
0$
0<
#1650000
1$
1<
b1000111 L
b1000011 P
#1660000
0$
0<
#1670000
1$
1<
b1001000 L
b1000100 P
#1680000
0$
0<
#1690000
1$
1<
b1001001 L
b1000101 P
#1700000
0$
0<
#1710000
1$
1<
b1001010 L
b1000110 P
#1720000
0$
0<
#1730000
1$
1<
b1001011 L
b1000111 P
#1740000
0$
0<
#1750000
1$
1<
b1001100 L
b1001000 P
#1760000
0$
0<
#1770000
1$
1<
b1001101 L
b1001001 P
#1780000
0$
0<
#1790000
1$
1<
b1001110 L
b1001010 P
#1800000
0$
0<
#1810000
1$
1<
b1001111 L
b1001011 P
#1820000
0$
0<
#1830000
1$
1<
b1010000 L
b1001100 P
#1840000
0$
0<
#1850000
1$
1<
b1010001 L
b1001101 P
#1860000
0$
0<
#1870000
1$
1<
b1010010 L
b1001110 P
#1880000
0$
0<
#1890000
1$
1<
b1010011 L
b1001111 P
#1900000
0$
0<
#1910000
1$
1<
b1010100 L
b1010000 P
#1920000
0$
0<
#1930000
1$
1<
b1010101 L
b1010001 P
#1940000
0$
0<
#1950000
1$
1<
b1010110 L
b1010010 P
#1960000
0$
0<
#1970000
1$
1<
b1010111 L
b1010011 P
#1980000
0$
0<
#1990000
1$
1<
b1011000 L
b1010100 P
#2000000
0$
0<
#2010000
1$
1<
b1011001 L
b1010101 P
#2020000
0$
0<
#2030000
1$
1<
b1011010 L
b1010110 P
#2040000
0$
0<
#2050000
1$
1<
b1011011 L
b1010111 P
#2060000
0$
0<
#2070000
1$
1<
b1011100 L
b1011000 P
#2080000
0$
0<
#2090000
1$
1<
b1011101 L
b1011001 P
#2100000
0$
0<
#2110000
1$
1<
b1011110 L
b1011010 P
#2120000
0$
0<
#2130000
1$
1<
b1011111 L
b1011011 P
#2140000
0$
0<
#2150000
1$
1<
b1100000 L
b1011100 P
#2160000
0$
0<
#2170000
1$
1<
b1100001 L
b1011101 P
#2180000
0$
0<
#2190000
1$
1<
b1100010 L
b1011110 P
#2200000
0$
0<
#2210000
1$
1<
b1100011 L
b1011111 P
#2220000
0$
0<
#2230000
1$
1<
b1100100 L
b1100000 P
#2240000
0$
0<
#2250000
1$
1<
b1100101 L
b1100001 P
#2260000
0$
0<
#2270000
1$
1<
b1100110 L
b1100010 P
#2280000
0$
0<
#2290000
1$
1<
b1100111 L
b1100011 P
#2300000
0$
0<
#2310000
1$
1<
b1101000 L
b1100100 P
#2320000
0$
0<
#2330000
1$
1<
b1101001 L
b1100101 P
#2340000
0$
0<
#2350000
1$
1<
b1101010 L
b1100110 P
#2360000
0$
0<
#2370000
1$
1<
b1101011 L
b1100111 P
#2380000
0$
0<
#2390000
1$
1<
b1101100 L
b1101000 P
#2400000
0$
0<
#2410000
1$
1<
b1101101 L
b1101001 P
#2420000
0$
0<
#2430000
1$
1<
b1101110 L
b1101010 P
#2440000
0$
0<
#2450000
1$
1<
b1101111 L
b1101011 P
#2460000
0$
0<
#2470000
1$
1<
b1110000 L
b1101100 P
#2480000
0$
0<
#2490000
1$
1<
b1110001 L
b1101101 P
#2500000
0$
0<
#2510000
1$
1<
b1110010 L
b1101110 P
#2520000
0$
0<
#2530000
1$
1<
b1110011 L
b1101111 P
#2540000
0$
0<
#2550000
1$
1<
b1110100 L
b1110000 P
#2560000
0$
0<
#2570000
1$
1<
b1110101 L
b1110001 P
#2580000
0$
0<
#2590000
1$
1<
b1110110 L
b1110010 P
#2600000
0$
0<
#2610000
1$
1<
b1110111 L
b1110011 P
#2620000
0$
0<
#2630000
1$
1<
b1111000 L
b1110100 P
#2640000
0$
0<
#2650000
1$
1<
b1111001 L
b1110101 P
#2660000
0$
0<
#2670000
1$
1<
b1111010 L
b1110110 P
#2680000
0$
0<
#2690000
1$
1<
b1111011 L
b1110111 P
#2700000
0$
0<
#2710000
1$
1<
b1111100 L
b1111000 P
#2720000
0$
0<
#2730000
1$
1<
b1111101 L
b1111001 P
#2740000
0$
0<
#2750000
1$
1<
b1111110 L
b1111010 P
#2760000
0$
0<
#2770000
1$
1<
b1111111 L
b1111011 P
#2780000
0$
0<
#2790000
1$
1<
b10000000 L
b1111100 P
#2800000
0$
0<
#2810000
1$
1<
b10000001 L
b1111101 P
#2820000
0$
0<
#2830000
1$
1<
b10000010 L
b1111110 P
#2840000
0$
0<
#2850000
1$
1<
b10000011 L
b1111111 P
#2860000
0$
0<
#2870000
1$
1<
b10000100 L
b10000000 P
#2880000
0$
0<
#2890000
1$
1<
b10000101 L
b10000001 P
#2900000
0$
0<
#2910000
1$
1<
b10000110 L
b10000010 P
#2920000
0$
0<
#2930000
1$
1<
b10000111 L
b10000011 P
#2940000
0$
0<
#2950000
1$
1<
b10001000 L
b10000100 P
#2960000
0$
0<
#2970000
1$
1<
b10001001 L
b10000101 P
#2980000
0$
0<
#2990000
1$
1<
b10001010 L
b10000110 P
#3000000
0$
0<
#3010000
1$
1<
b10001011 L
b10000111 P
#3020000
0$
0<
#3030000
1$
1<
b10001100 L
b10001000 P
#3040000
0$
0<
#3050000
1$
1<
b10001101 L
b10001001 P
#3060000
0$
0<
#3070000
1$
1<
b10001110 L
b10001010 P
#3080000
0$
0<
#3090000
1$
1<
b10001111 L
b10001011 P
#3100000
0$
0<
#3110000
1$
1<
b10010000 L
b10001100 P
#3120000
0$
0<
#3130000
1$
1<
b10010001 L
b10001101 P
#3140000
0$
0<
#3150000
1$
1<
b10010010 L
b10001110 P
#3160000
0$
0<
#3170000
1$
1<
b10010011 L
b10001111 P
#3180000
0$
0<
#3190000
1$
1<
b10010100 L
b10010000 P
#3200000
0$
0<
#3210000
1$
1<
b10010101 L
b10010001 P
#3220000
0$
0<
#3230000
1$
1<
b10010110 L
b10010010 P
#3240000
0$
0<
#3250000
1$
1<
b10010111 L
b10010011 P
#3260000
0$
0<
#3270000
1$
1<
b10011000 L
b10010100 P
#3280000
0$
0<
#3290000
1$
1<
b10011001 L
b10010101 P
#3300000
0$
0<
#3310000
1$
1<
b10011010 L
b10010110 P
#3320000
0$
0<
#3330000
1$
1<
b10011011 L
b10010111 P
#3340000
0$
0<
#3350000
1$
1<
b10011100 L
b10011000 P
#3360000
0$
0<
#3370000
1$
1<
b10011101 L
b10011001 P
#3380000
0$
0<
#3390000
1$
1<
b10011110 L
b10011010 P
#3400000
0$
0<
#3410000
1$
1<
b10011111 L
b10011011 P
#3420000
0$
0<
#3430000
1$
1<
b10100000 L
b10011100 P
#3440000
0$
0<
#3450000
1$
1<
b10100001 L
b10011101 P
#3460000
0$
0<
#3470000
1$
1<
b10100010 L
b10011110 P
#3480000
0$
0<
#3490000
1$
1<
b10100011 L
b10011111 P
#3500000
0$
0<
#3510000
1$
1<
b10100100 L
b10100000 P
#3520000
0$
0<
#3530000
1$
1<
b10100101 L
b10100001 P
#3540000
0$
0<
#3550000
1$
1<
b10100110 L
b10100010 P
#3560000
0$
0<
#3570000
1$
1<
b10100111 L
b10100011 P
#3580000
0$
0<
#3590000
1$
1<
b10101000 L
b10100100 P
#3600000
0$
0<
#3610000
1$
1<
b10101001 L
b10100101 P
#3620000
0$
0<
#3630000
1$
1<
b10101010 L
b10100110 P
#3640000
0$
0<
#3650000
1$
1<
b10101011 L
b10100111 P
#3660000
0$
0<
#3670000
1$
1<
b10101100 L
b10101000 P
#3680000
0$
0<
#3690000
1$
1<
b10101101 L
b10101001 P
#3700000
0$
0<
#3710000
1$
1<
b10101110 L
b10101010 P
#3720000
0$
0<
#3730000
1$
1<
b10101111 L
b10101011 P
#3740000
0$
0<
#3750000
1$
1<
b10110000 L
b10101100 P
#3760000
0$
0<
#3770000
1$
1<
b10110001 L
b10101101 P
#3780000
0$
0<
#3790000
1$
1<
b10110010 L
b10101110 P
#3800000
0$
0<
#3810000
1$
1<
b10110011 L
b10101111 P
#3820000
0$
0<
#3830000
1$
1<
b10110100 L
b10110000 P
#3840000
0$
0<
#3850000
1$
1<
b10110101 L
b10110001 P
#3860000
0$
0<
#3870000
1$
1<
b10110110 L
b10110010 P
#3880000
0$
0<
#3890000
1$
1<
b10110111 L
b10110011 P
#3900000
0$
0<
#3910000
1$
1<
b10111000 L
b10110100 P
#3920000
0$
0<
#3930000
1$
1<
b10111001 L
b10110101 P
#3940000
0$
0<
#3950000
1$
1<
b10111010 L
b10110110 P
#3960000
0$
0<
#3970000
1$
1<
b10111011 L
b10110111 P
#3980000
0$
0<
#3990000
1$
1<
b10111100 L
b10111000 P
#4000000
0$
0<
#4010000
1$
1<
b10111101 L
b10111001 P
#4020000
0$
0<
#4030000
1$
1<
b10111110 L
b10111010 P
#4040000
0$
0<
#4050000
1$
1<
b10111111 L
b10111011 P
#4060000
0$
0<
#4070000
1$
1<
b11000000 L
b10111100 P
#4080000
0$
0<
#4090000
1$
1<
b11000001 L
b10111101 P
#4100000
0$
0<
#4110000
1$
1<
b11000010 L
b10111110 P
#4120000
0$
0<
#4130000
1$
1<
b11000011 L
b10111111 P
#4140000
0$
0<
#4150000
1$
1<
b11000100 L
b11000000 P
#4160000
0$
0<
#4170000
1$
1<
b11000101 L
b11000001 P
#4180000
0$
0<
#4190000
1$
1<
b11000110 L
b11000010 P
#4200000
0$
0<
#4210000
1$
1<
b11000111 L
b11000011 P
#4220000
0$
0<
#4230000
1$
1<
b11001000 L
b11000100 P
#4240000
0$
0<
#4250000
1$
1<
b11001001 L
b11000101 P
#4260000
0$
0<
#4270000
1$
1<
b11001010 L
b11000110 P
#4280000
0$
0<
#4290000
1$
1<
b11001011 L
b11000111 P
#4300000
0$
0<
#4310000
1$
1<
b11001100 L
b11001000 P
#4320000
0$
0<
#4330000
1$
1<
b11001101 L
b11001001 P
#4340000
0$
0<
#4350000
1$
1<
b11001110 L
b11001010 P
#4360000
0$
0<
#4370000
1$
1<
b11001111 L
b11001011 P
#4380000
0$
0<
#4390000
1$
1<
b11010000 L
b11001100 P
#4400000
0$
0<
#4410000
1$
1<
b11010001 L
b11001101 P
#4420000
0$
0<
#4430000
1$
1<
b11010010 L
b11001110 P
#4440000
0$
0<
#4450000
1$
1<
b11010011 L
b11001111 P
#4460000
0$
0<
#4470000
1$
1<
b11010100 L
b11010000 P
#4480000
0$
0<
#4490000
1$
1<
b11010101 L
b11010001 P
#4500000
0$
0<
#4510000
1$
1<
b11010110 L
b11010010 P
#4520000
0$
0<
#4530000
1$
1<
b11010111 L
b11010011 P
#4540000
0$
0<
#4550000
1$
1<
b11011000 L
b11010100 P
#4560000
0$
0<
#4570000
1$
1<
b11011001 L
b11010101 P
#4580000
0$
0<
#4590000
1$
1<
b11011010 L
b11010110 P
#4600000
0$
0<
#4610000
1$
1<
b11011011 L
b11010111 P
#4620000
0$
0<
#4630000
1$
1<
b11011100 L
b11011000 P
#4640000
0$
0<
#4650000
1$
1<
b11011101 L
b11011001 P
#4660000
0$
0<
#4670000
1$
1<
b11011110 L
b11011010 P
#4680000
0$
0<
#4690000
1$
1<
b11011111 L
b11011011 P
#4700000
0$
0<
#4710000
1$
1<
b11100000 L
b11011100 P
#4720000
0$
0<
#4730000
1$
1<
b11100001 L
b11011101 P
#4740000
0$
0<
#4750000
1$
1<
b11100010 L
b11011110 P
#4760000
0$
0<
#4770000
1$
1<
b11100011 L
b11011111 P
#4780000
0$
0<
#4790000
1$
1<
b11100100 L
b11100000 P
#4800000
0$
0<
#4810000
1$
1<
b11100101 L
b11100001 P
#4820000
0$
0<
#4830000
1$
1<
b11100110 L
b11100010 P
#4840000
0$
0<
#4850000
1$
1<
b11100111 L
b11100011 P
#4860000
0$
0<
#4870000
1$
1<
b11101000 L
b11100100 P
#4880000
0$
0<
#4890000
1$
1<
b11101001 L
b11100101 P
#4900000
0$
0<
#4910000
1$
1<
b11101010 L
b11100110 P
#4920000
0$
0<
#4930000
1$
1<
b11101011 L
b11100111 P
#4940000
0$
0<
#4950000
1$
1<
b11101100 L
b11101000 P
#4960000
0$
0<
#4970000
1$
1<
b11101101 L
b11101001 P
#4980000
0$
0<
#4990000
1$
1<
b11101110 L
b11101010 P
#5000000
0$
0<
#5010000
1$
1<
b11101111 L
b11101011 P
#5020000
0$
0<
#5030000
1$
1<
b11110000 L
b11101100 P
#5040000
0$
0<
#5050000
1$
1<
b11110001 L
b11101101 P
#5060000
0$
0<
#5070000
1$
1<
b11110010 L
b11101110 P
#5080000
0$
0<
#5090000
1$
1<
b11110011 L
b11101111 P
#5100000
0$
0<
#5110000
1$
1<
b11110100 L
b11110000 P
#5120000
0$
0<
#5130000
1$
1<
b11110101 L
b11110001 P
#5140000
0$
0<
#5150000
1$
1<
b11110110 L
b11110010 P
#5160000
0$
0<
#5170000
1$
1<
b11110111 L
b11110011 P
#5180000
0$
0<
#5190000
1$
1<
b11111000 L
b11110100 P
#5200000
0$
0<
#5210000
1$
1<
b11111001 L
b11110101 P
#5220000
0$
0<
#5230000
1$
1<
b11111010 L
b11110110 P
#5240000
0$
0<
#5250000
1$
1<
b11111011 L
b11110111 P
#5260000
0$
0<
#5270000
1$
1<
b11111100 L
b11111000 P
#5280000
0$
0<
#5290000
1$
1<
b11111101 L
b11111001 P
#5300000
0$
0<
#5310000
1$
1<
b11111110 L
b11111010 P
#5320000
0$
0<
#5330000
1$
1<
b11111111 L
b11111011 P
#5340000
0$
0<
#5350000
1$
1<
b100000000 L
b11111100 P
#5360000
0$
0<
#5370000
1$
1<
b100000001 L
b11111101 P
#5380000
0$
0<
#5390000
1$
1<
b100000010 L
b11111110 P
#5400000
0$
0<
#5410000
1$
1<
b100000011 L
b11111111 P
#5420000
0$
0<
#5430000
1$
1<
b100000100 L
b100000000 P
#5440000
0$
0<
#5450000
1$
1<
b100000101 L
b100000001 P
#5460000
0$
0<
#5470000
1$
1<
b100000110 L
b100000010 P
#5480000
0$
0<
#5490000
1$
1<
b100000111 L
b100000011 P
#5500000
0$
0<
#5510000
1$
1<
b100001000 L
b100000100 P
#5520000
0$
0<
#5530000
1$
1<
b100001001 L
b100000101 P
#5540000
0$
0<
#5550000
1$
1<
b100001010 L
b100000110 P
#5560000
0$
0<
#5570000
1$
1<
b100001011 L
b100000111 P
#5580000
0$
0<
#5590000
1$
1<
b100001100 L
b100001000 P
#5600000
0$
0<
#5610000
1$
1<
b100001101 L
b100001001 P
#5620000
0$
0<
